hgsTools-0.2.71a1.dist-info/WHEEL
hgsTools-0.2.71a1.dist-info/RECORD
hgsTools-0.2.71a1.dist-info/DESCRIPTION.rst
hgsTools-0.2.71a1.dist-info/METADATA
hgsTools-0.2.71a1.dist-info/top_level.txt
hgsTools-0.2.71a1.dist-info/metadata.json
hgsTools/__init__.py
hgsTools/messaging/__init__.py
hgsTools/auxiliary/s3tools.py
hgsTools/auxiliary/__init__.py
