Metadata-Version: 2.0
Name: hgsTools
Version: 0.2.71a1
Summary: hgsTools Python project
Home-page: UNKNOWN
Author: Andrei
Author-email: karandash8@gmail.com
License: MIT
Keywords: hgs
Platform: UNKNOWN
Classifier: Development Status :: 3 - Alpha
Classifier: Intended Audience :: Developers
Classifier: Topic :: Software Development :: Libraries
Classifier: License :: OSI Approved :: MIT License
Classifier: Programming Language :: Python :: 2.7
Requires-Dist: kombu
Requires-Dist: netifaces (==0.10.4)
